[
  {
    "id": 1,
    "create_user": "张三",
    "content": "这个视频不错呀，挺好看的",
    "resouce_name":"今天是个好日子.mp4",
    "statu":"有效",
    "create_date":"2015-8-28"
  },
  {
    "id": 1,
    "create_user": "张三",
    "content": "这个视频不错呀，挺好看的",
    "resouce_name":"今天是个好日子.mp4",
    "statu":"有效",
    "create_date":"2015-8-28"
  },
  {
    "id": 1,
    "create_user": "张三",
    "content": "这个视频不错呀，挺好看的",
    "resouce_name":"今天是个好日子.mp4",
    "statu":"有效",
    "create_date":"2015-8-28"
  },
  {
    "id": 1,
    "create_user": "张三",
    "content": "这个视频不错呀，挺好看的",
    "resouce_name":"今天是个好日子.mp4",
    "statu":"有效",
    "create_date":"2015-8-28"
  },
  {
    "id": 1,
    "create_user": "张三",
    "content": "这个视频不错呀，挺好看的",
    "resouce_name":"今天是个好日子.mp4",
    "statu":"有效",
    "create_date":"2015-8-28"
  },
  {
    "id": 1,
    "create_user": "张三",
    "content": "这个视频不错呀，挺好看的",
    "resouce_name":"今天是个好日子.mp4",
    "statu":"有效",
    "create_date":"2015-8-28"
  },
  {
    "id": 1,
    "create_user": "张三",
    "content": "这个视频不错呀，挺好看的",
    "resouce_name":"今天是个好日子.mp4",
    "statu":"有效",
    "create_date":"2015-8-28"
  },
  {
    "id": 1,
    "create_user": "张三",
    "content": "这个视频不错呀，挺好看的",
    "resouce_name":"今天是个好日子.mp4",
    "statu":"有效",
    "create_date":"2015-8-28"
  }
]
